Metadata-Version: 1.0
Name: Gu-Bi-GB
Version: 0.1
Summary: Gaussian and Binomial distributions
Home-page: UNKNOWN
Author: Ahmad
Author-email: UNKNOWN
License: UNKNOWN
Platform: UNKNOWN
